EtsyScraperLib/__init__.py
EtsyScraperLib/product.py
EtsyScraperLib/store.py
EtsyScraperLib/test.py
EtsyScraperLib/text_format.py
etsyscraper/__init__.py
etsyscraper/product.py
etsyscraper/store.py
etsyscraper/test.py
etsyscraper/text_format.py
EtsyScraperLib-0.0.9.dist-info/LICENSE
EtsyScraperLib-0.0.9.dist-info/METADATA
EtsyScraperLib-0.0.9.dist-info/WHEEL
EtsyScraperLib-0.0.9.dist-info/top_level.txt
EtsyScraperLib-0.0.9.dist-info/RECORD
