Metadata-Version: 2.1
Name: EtsyScraperLib
Version: 0.0.9
Summary: A data scraper for Etsy stores
Author: v0rkath
Author-email: <x02@fastmail.com>
License: MIT
Keywords: etsy,scraper,data,store,shop,price
Classifier: Development Status :: 5 - Production/Stable
Classifier: Intended Audience :: Developers
Classifier: Operating System :: Microsoft :: Windows :: Windows 10
Classifier: License :: OSI Approved :: MIT License
Classifier: Programming Language :: Python :: 3.7
License-File: LICENSE
Requires-Dist: beautifulsoup4
Requires-Dist: requests
